splat_llm/__init__.py
splat_llm/__main__.py
splat_llm/database.py
splat_llm/normalize.py
splat_llm/styles.py
splat_llm/version.py
splatllm-0.1.0.dist-info/METADATA
splatllm-0.1.0.dist-info/WHEEL
splatllm-0.1.0.dist-info/entry_points.txt
splatllm-0.1.0.dist-info/licenses/LICENSE
splatllm-0.1.0.dist-info/RECORD
