Metadata-Version: 2.4
Name: SplatLLM
Version: 0.1.0
Summary: SplatLLM makes text generated by large language models (LLMs) appear more authentically human via heuristic-based formatting.
Project-URL: Homepage, https://github.com/theobjectivedad/splat-llm
Project-URL: Issues, https://github.com/theobjectivedad/splat-llm/issues
Author-email: The Objective Dad <theobjectivedad@gmail.com>
License-Expression: Apache-2.0
License-File: LICENSE
Keywords: filter,invisible,mcp,text,watermark
Classifier: Development Status :: 3 - Alpha
Classifier: Environment :: Console
Classifier: Operating System :: OS Independent
Classifier: Programming Language :: Python :: 3
Classifier: Topic :: Text Processing :: Filters
Classifier: Topic :: Utilities
Requires-Python: >=3.10.12
Requires-Dist: beautifulsoup4>=4.13.4
Requires-Dist: click
Requires-Dist: rich>=14.0.0
